jptk/__init__.py
jptk/currency.py
jptk/date.py
python_jptk-1.0.0.dist-info/LICENSE.txt
python_jptk-1.0.0.dist-info/METADATA
python_jptk-1.0.0.dist-info/WHEEL
python_jptk-1.0.0.dist-info/top_level.txt
python_jptk-1.0.0.dist-info/RECORD
